README.md
setup.py
zzzing/__init__.py
zzzing/__main__.py
zzzing.egg-info/PKG-INFO
zzzing.egg-info/SOURCES.txt
zzzing.egg-info/dependency_links.txt
zzzing.egg-info/entry_points.txt
zzzing.egg-info/requires.txt
zzzing.egg-info/top_level.txt