Metadata-Version: 2.1
Name: zzzing
Version: 0.4.7
Summary: zzzing CLI by xuanzhi33
Home-page: https://zzzing.cn
Author: xuanzhi33
Author-email: xuanzhi33@qq.com
License: GPL-3.0
Platform: UNKNOWN
Classifier: Programming Language :: Python :: 3
Classifier: License :: OSI Approved :: GNU General Public License v3 (GPLv3)
Classifier: Operating System :: OS Independent
Requires-Python: >=3.6
